authz/__init__.py
authz/exceptions.py
authz/middleware.py
authz/utils.py
graphql_authz-0.1.2.dist-info/AUTHORS.rst
graphql_authz-0.1.2.dist-info/LICENSE
graphql_authz-0.1.2.dist-info/METADATA
graphql_authz-0.1.2.dist-info/WHEEL
graphql_authz-0.1.2.dist-info/top_level.txt
graphql_authz-0.1.2.dist-info/RECORD
