Metadata-Version: 2.1
Name: graphql-authz
Version: 0.1.2
Summary: Authorization middleware for GraphQL.
Home-page: https://github.com/Checho3388/graphql-authz
Author: Ezequiel Grondona
Author-email: ezequiel.grondona@gmail.com
License: MIT license
Keywords: graphql
Platform: UNKNOWN
Classifier: Development Status :: 2 - Pre-Alpha
Classifier: Intended Audience :: Developers
Classifier: Topic :: Software Development :: Libraries
Classifier: License :: OSI Approved :: MIT License
Classifier: Natural Language :: English
Classifier: Programming Language :: Python :: 3
Classifier: Programming Language :: Python :: 3.6
Classifier: Programming Language :: Python :: 3.7
Classifier: Programming Language :: Python :: 3.8
Requires-Python: >=3.6
License-File: LICENSE
License-File: AUTHORS.rst
Requires-Dist: casbin (==1.9.3)
